separability_index/__init__.py
separability_index/separability_index.py
separability_index-0.1.0.dist-info/LICENSE
separability_index-0.1.0.dist-info/METADATA
separability_index-0.1.0.dist-info/WHEEL
separability_index-0.1.0.dist-info/top_level.txt
separability_index-0.1.0.dist-info/RECORD
