Metadata-Version: 2.1
Name: separability-index
Version: 0.1.0
Summary: A suite of tools to assess the separability of two datasets.
Home-page: https://github.com/RPretellD/separability_index
Author: A. Renmin Pretell Ductram, Scott J. Brandenberg
Author-email: rpretell@unr.edu, sjbrandenberg@ucla.edu
License: MIT
Keywords: separability
Classifier: Programming Language :: Python :: 3
Classifier: License :: OSI Approved :: MIT License
Requires-Python: >=3.6
License-File: LICENSE
Requires-Dist: numpy
